README.md
setup.py
busca_inf_pdf/__init__.py
busca_inf_pdf/busca_inf_pdf.py
busca_inf_pdf.egg-info/PKG-INFO
busca_inf_pdf.egg-info/SOURCES.txt
busca_inf_pdf.egg-info/dependency_links.txt
busca_inf_pdf.egg-info/requires.txt
busca_inf_pdf.egg-info/top_level.txt