Metadata-Version: 2.1
Name: busca-inf-pdf
Version: 0.0.1
Summary: Pacote desenvolvido para buscar informações em arquivos pdf
Home-page: https://github.com/RoSchilling/busca_inf_pdf
Author: Rodrigo Schilling
Author-email: rodrigo.schilling98@gmail.com
